limoo/__init__.py
limoo/driver.py
limoo/exceptions.py
limoo/entities/__init__.py
limoo/entities/conversations.py
limoo/entities/files.py
limoo/entities/messages.py
limoo/entities/users.py
limoo/entities/workspaces.py
limoo_sdk-0.2.4.dist-info/WHEEL
limoo_sdk-0.2.4.dist-info/METADATA
limoo_sdk-0.2.4.dist-info/RECORD
