Metadata-Version: 2.1
Name: limoo-sdk
Version: 0.2.4
Summary: An SDK to work with Limoo
Home-page: https://github.com/limoo-im/python-sdk
Keywords: limoo,sdk
Author: Soroosh Chabi
Author-email: chabi@limoo.im
Requires-Python: >=3.7
Classifier: Development Status :: 2 - Pre-Alpha
Classifier: Framework :: AsyncIO
Classifier: Intended Audience :: Developers
Classifier: Operating System :: OS Independent
Classifier: Programming Language :: Python :: 3.7
Classifier: Programming Language :: Python :: 3.8
Classifier: Programming Language :: Python :: 3.9
Classifier: Topic :: Communications :: Chat
Classifier: Topic :: Software Development :: Libraries :: Python Modules
Requires-Dist: aiohttp~=3.7
